seiryu/__init__.py
seiryu/seiryu.py
seiryu-1.0.18.dist-info/LICENSE
seiryu-1.0.18.dist-info/METADATA
seiryu-1.0.18.dist-info/WHEEL
seiryu-1.0.18.dist-info/entry_points.txt
seiryu-1.0.18.dist-info/top_level.txt
seiryu-1.0.18.dist-info/RECORD
