Metadata-Version: 2.1
Name: seiryu
Version: 1.0.18
Summary: The Pinnacle of Advanced Hash Generator
Home-page: https://github.com/veilwr4ith/Seiryu
Author: Veilwr4ith
Author-email: hacktheveil@gmail.com
License: UNKNOWN
Platform: UNKNOWN
Classifier: Programming Language :: Python :: 3
Classifier: License :: OSI Approved :: GNU General Public License v3 (GPLv3)
Classifier: Operating System :: OS Independent
Requires-Python: >=3.10
License-File: LICENSE
Requires-Dist: argon2
Requires-Dist: argon2-cffi
Requires-Dist: argon2-cffi-bindings
Requires-Dist: bcrypt
Requires-Dist: cffi
Requires-Dist: numpy
Requires-Dist: passlib
Requires-Dist: siphashc
Requires-Dist: spookyhash
Requires-Dist: uuid
Requires-Dist: xxhash
